{
  "last_updated": "2026-05-29T12:49:37.481Z",
  "watchlist": [
    {
      "symbol": "MSCI",
      "added_date": "2026-05-29",
      "source": "earnings",
      "earnings_date": "2026-04-21",
      "earnings_gain_pct": 5.37,
      "earnings_close": 595.2404,
      "high_30d": 566.5041,
      "status": "watching",
      "sma_direction": "gaining",
      "current_sma": 608.51,
      "prev_sma": 601.135,
      "trigger_date": null,
      "trigger_price": null,
      "trigger_sma": null,
      "last_checked": "2026-05-29T11:34:40.919077+00:00"
    },
    {
      "symbol": "GWW",
      "added_date": "2026-05-29",
      "source": "earnings",
      "earnings_date": "2026-05-07",
      "earnings_gain_pct": 5.49,
      "earnings_close": 1231.6091,
      "high_30d": 1169.844,
      "status": "watching",
      "sma_direction": "declining",
      "current_sma": 1248.856,
      "prev_sma": 1248.916,
      "trigger_date": null,
      "trigger_price": null,
      "trigger_sma": null,
      "last_checked": "2026-05-29T11:34:41.073829+00:00"
    },
    {
      "symbol": "IEX",
      "added_date": "2026-05-29",
      "source": "earnings",
      "earnings_date": "2026-04-29",
      "earnings_gain_pct": 5.83,
      "earnings_close": 216.5683,
      "high_30d": 206.6537,
      "status": "watching",
      "sma_direction": "declining",
      "current_sma": 210.846,
      "prev_sma": 210.952,
      "trigger_date": null,
      "trigger_price": null,
      "trigger_sma": null,
      "last_checked": "2026-05-29T11:34:41.206850+00:00"
    },
    {
      "symbol": "BIIB",
      "added_date": "2026-05-29",
      "source": "earnings",
      "earnings_date": "2026-04-29",
      "earnings_gain_pct": 6,
      "earnings_close": 194.38,
      "high_30d": 191.06,
      "status": "watching",
      "sma_direction": "gaining",
      "current_sma": 196.389,
      "prev_sma": 195.995,
      "trigger_date": null,
      "trigger_price": null,
      "trigger_sma": null,
      "last_checked": "2026-05-29T11:34:41.328099+00:00"
    },
    {
      "symbol": "GNRC",
      "added_date": "2026-05-29",
      "source": "earnings",
      "earnings_date": "2026-04-29",
      "earnings_gain_pct": 16.49,
      "earnings_close": 252.92,
      "high_30d": 220.93,
      "status": "watching",
      "sma_direction": "gaining",
      "current_sma": 278.24,
      "prev_sma": 277.74,
      "trigger_date": null,
      "trigger_price": null,
      "trigger_sma": null,
      "last_checked": "2026-05-29T11:34:41.451208+00:00"
    },
    {
      "symbol": "HWM",
      "added_date": "2026-05-29",
      "source": "earnings",
      "earnings_date": "2026-05-07",
      "earnings_gain_pct": 6.28,
      "earnings_close": 272.42,
      "high_30d": 257.9164,
      "status": "watching",
      "sma_direction": "declining",
      "current_sma": 259.697,
      "prev_sma": 259.773,
      "trigger_date": null,
      "trigger_price": null,
      "trigger_sma": null,
      "last_checked": "2026-05-29T11:34:41.579680+00:00"
    },
    {
      "symbol": "IRM",
      "added_date": "2026-05-29",
      "source": "earnings",
      "earnings_date": "2026-04-30",
      "earnings_gain_pct": 10.02,
      "earnings_close": 125.99,
      "high_30d": 120.53,
      "status": "watching",
      "sma_direction": "declining",
      "current_sma": 127.574,
      "prev_sma": 127.892,
      "trigger_date": null,
      "trigger_price": null,
      "trigger_sma": null,
      "last_checked": "2026-05-29T11:34:41.705981+00:00"
    },
    {
      "symbol": "ZBRA",
      "added_date": "2026-05-29",
      "source": "earnings",
      "earnings_date": "2026-05-12",
      "earnings_gain_pct": 11.44,
      "earnings_close": 241.79,
      "high_30d": 237.3,
      "status": "watching",
      "sma_direction": "declining",
      "current_sma": 250.254,
      "prev_sma": 251.265,
      "trigger_date": null,
      "trigger_price": null,
      "trigger_sma": null,
      "last_checked": "2026-05-29T11:34:41.841469+00:00"
    },
    {
      "symbol": "PWR",
      "added_date": "2026-05-29",
      "source": "earnings",
      "earnings_date": "2026-04-30",
      "earnings_gain_pct": 15.78,
      "earnings_close": 727.77,
      "high_30d": 637.28,
      "status": "watching",
      "sma_direction": "declining",
      "current_sma": 735.92,
      "prev_sma": 738.368,
      "trigger_date": null,
      "trigger_price": null,
      "trigger_sma": null,
      "last_checked": "2026-05-29T11:34:41.959917+00:00"
    },
    {
      "symbol": "FFIV",
      "added_date": "2026-05-29",
      "source": "earnings",
      "earnings_date": "2026-04-28",
      "earnings_gain_pct": 8.02,
      "earnings_close": 328.15,
      "high_30d": 315.56,
      "status": "watching",
      "sma_direction": "declining",
      "current_sma": 390.858,
      "prev_sma": 393.8422,
      "trigger_date": null,
      "trigger_price": null,
      "trigger_sma": null,
      "last_checked": "2026-05-29T11:34:42.340503+00:00"
    },
    {
      "symbol": "STX",
      "added_date": "2026-05-29",
      "source": "earnings",
      "earnings_date": "2026-04-28",
      "earnings_gain_pct": 11.1,
      "earnings_close": 643.3,
      "high_30d": 595.86,
      "status": "watching",
      "sma_direction": "gaining",
      "current_sma": 873.627,
      "prev_sma": 866.791,
      "trigger_date": null,
      "trigger_price": null,
      "trigger_sma": null,
      "last_checked": "2026-05-29T11:34:42.498074+00:00"
    },
    {
      "symbol": "TXN",
      "added_date": "2026-05-29",
      "source": "earnings",
      "earnings_date": "2026-04-22",
      "earnings_gain_pct": 19.43,
      "earnings_close": 280.8032,
      "high_30d": 235.1154,
      "status": "watching",
      "sma_direction": "declining",
      "current_sma": 318.753,
      "prev_sma": 320.248,
      "trigger_date": null,
      "trigger_price": null,
      "trigger_sma": null,
      "last_checked": "2026-05-29T11:34:42.672439+00:00"
    },
    {
      "symbol": "SNDK",
      "added_date": "2026-05-29",
      "source": "earnings",
      "earnings_date": "2026-04-30",
      "earnings_gain_pct": 8.25,
      "earnings_close": 1187,
      "high_30d": 1096.51,
      "status": "watching",
      "sma_direction": "gaining",
      "current_sma": 1616.767,
      "prev_sma": 1607.571,
      "trigger_date": null,
      "trigger_price": null,
      "trigger_sma": null,
      "last_checked": "2026-05-29T11:34:42.809474+00:00"
    },
    {
      "symbol": "DVA",
      "added_date": "2026-05-29",
      "source": "earnings",
      "earnings_date": "2026-05-05",
      "earnings_gain_pct": 23.46,
      "earnings_close": 193.88,
      "high_30d": 157.04,
      "status": "watching",
      "sma_direction": "gaining",
      "current_sma": 196.12,
      "prev_sma": 195.91,
      "trigger_date": null,
      "trigger_price": null,
      "trigger_sma": null,
      "last_checked": "2026-05-29T11:34:42.960024+00:00"
    },
    {
      "symbol": "SMCI",
      "added_date": "2026-05-29",
      "source": "earnings",
      "earnings_date": "2026-05-05",
      "earnings_gain_pct": 24.54,
      "earnings_close": 34.66,
      "high_30d": 29.18,
      "status": "watching",
      "sma_direction": "gaining",
      "current_sma": 39.238,
      "prev_sma": 38.364,
      "trigger_date": null,
      "trigger_price": null,
      "trigger_sma": null,
      "last_checked": "2026-05-29T11:34:43.091581+00:00"
    },
    {
      "symbol": "CPAY",
      "added_date": "2026-05-29",
      "source": "earnings",
      "earnings_date": "2026-05-07",
      "earnings_gain_pct": 12.51,
      "earnings_close": 343.99,
      "high_30d": 337.34,
      "status": "watching",
      "sma_direction": "gaining",
      "current_sma": 352.367,
      "prev_sma": 350.9995,
      "trigger_date": null,
      "trigger_price": null,
      "trigger_sma": null,
      "last_checked": "2026-05-29T11:34:43.215703+00:00"
    },
    {
      "symbol": "IFF",
      "added_date": "2026-05-29",
      "source": "earnings",
      "earnings_date": "2026-05-05",
      "earnings_gain_pct": 17.18,
      "earnings_close": 82.93,
      "high_30d": 75.88,
      "status": "watching",
      "sma_direction": "gaining",
      "current_sma": 77.35,
      "prev_sma": 76.923,
      "trigger_date": null,
      "trigger_price": null,
      "trigger_sma": null,
      "last_checked": "2026-05-29T11:34:43.366038+00:00"
    },
    {
      "symbol": "ROST",
      "added_date": "2026-05-29",
      "source": "earnings",
      "earnings_date": "2026-05-21",
      "earnings_gain_pct": 8.11,
      "earnings_close": 234.81,
      "high_30d": 228.91,
      "status": "watching",
      "sma_direction": "declining",
      "current_sma": 231.522,
      "prev_sma": 232.829,
      "trigger_date": null,
      "trigger_price": null,
      "trigger_sma": null,
      "last_checked": "2026-05-29T11:34:43.492099+00:00"
    },
    {
      "symbol": "DHI",
      "added_date": "2026-05-29",
      "source": "earnings",
      "earnings_date": "2026-04-21",
      "earnings_gain_pct": 5.78,
      "earnings_close": 161.7107,
      "high_30d": 152.8774,
      "status": "watching",
      "sma_direction": "gaining",
      "current_sma": 146.857,
      "prev_sma": 146.36,
      "trigger_date": null,
      "trigger_price": null,
      "trigger_sma": null,
      "last_checked": "2026-05-29T11:34:43.878316+00:00"
    },
    {
      "symbol": "UNH",
      "added_date": "2026-05-29",
      "source": "earnings",
      "earnings_date": "2026-04-21",
      "earnings_gain_pct": 6.96,
      "earnings_close": 346.01,
      "high_30d": 324.63,
      "status": "watching",
      "sma_direction": "gaining",
      "current_sma": 382.318,
      "prev_sma": 381.494,
      "trigger_date": null,
      "trigger_price": null,
      "trigger_sma": null,
      "last_checked": "2026-05-29T11:34:44.014559+00:00"
    },
    {
      "symbol": "BA",
      "added_date": "2026-05-29",
      "source": "earnings",
      "earnings_date": "2026-04-22",
      "earnings_gain_pct": 5.53,
      "earnings_close": 231.28,
      "high_30d": 225.08,
      "status": "watching",
      "sma_direction": "gaining",
      "current_sma": 224.564,
      "prev_sma": 222.77,
      "trigger_date": null,
      "trigger_price": null,
      "trigger_sma": null,
      "last_checked": "2026-05-29T11:34:44.165815+00:00"
    },
    {
      "symbol": "GEV",
      "added_date": "2026-05-29",
      "source": "earnings",
      "earnings_date": "2026-04-22",
      "earnings_gain_pct": 13.75,
      "earnings_close": 1127.5601,
      "high_30d": 1002.75,
      "status": "watching",
      "sma_direction": "declining",
      "current_sma": 1031.769,
      "prev_sma": 1047.701,
      "trigger_date": null,
      "trigger_price": null,
      "trigger_sma": null,
      "last_checked": "2026-05-29T11:34:44.444564+00:00"
    },
    {
      "symbol": "BKR",
      "added_date": "2026-05-29",
      "source": "earnings",
      "earnings_date": "2026-04-23",
      "earnings_gain_pct": 6.9,
      "earnings_close": 68.7102,
      "high_30d": 64.2751,
      "status": "watching",
      "sma_direction": "declining",
      "current_sma": 64.476,
      "prev_sma": 64.948,
      "trigger_date": null,
      "trigger_price": null,
      "trigger_sma": null,
      "last_checked": "2026-05-29T11:34:44.731838+00:00"
    },
    {
      "symbol": "CMCSA",
      "added_date": "2026-05-29",
      "source": "earnings",
      "earnings_date": "2026-04-23",
      "earnings_gain_pct": 7.73,
      "earnings_close": 31.64,
      "high_30d": 30.2186,
      "status": "watching",
      "sma_direction": "gaining",
      "current_sma": 25.1975,
      "prev_sma": 25.1805,
      "trigger_date": null,
      "trigger_price": null,
      "trigger_sma": null,
      "last_checked": "2026-05-29T11:34:44.854170+00:00"
    },
    {
      "symbol": "INTC",
      "added_date": "2026-05-29",
      "source": "earnings",
      "earnings_date": "2026-04-23",
      "earnings_gain_pct": 23.6,
      "earnings_close": 82.54,
      "high_30d": 68.5,
      "status": "watching",
      "sma_direction": "declining",
      "current_sma": 121.115,
      "prev_sma": 121.292,
      "trigger_date": null,
      "trigger_price": null,
      "trigger_sma": null,
      "last_checked": "2026-05-29T11:34:45.136659+00:00"
    },
    {
      "symbol": "BEN",
      "added_date": "2026-05-29",
      "source": "earnings",
      "earnings_date": "2026-04-28",
      "earnings_gain_pct": 6.86,
      "earnings_close": 29.46,
      "high_30d": 27.73,
      "status": "watching",
      "sma_direction": "declining",
      "current_sma": 31.494,
      "prev_sma": 31.55,
      "trigger_date": null,
      "trigger_price": null,
      "trigger_sma": null,
      "last_checked": "2026-05-29T11:34:45.763938+00:00"
    },
    {
      "symbol": "CNC",
      "added_date": "2026-05-29",
      "source": "earnings",
      "earnings_date": "2026-04-28",
      "earnings_gain_pct": 13.95,
      "earnings_close": 49.57,
      "high_30d": 43.5,
      "status": "watching",
      "sma_direction": "gaining",
      "current_sma": 58.621,
      "prev_sma": 58.395,
      "trigger_date": null,
      "trigger_price": null,
      "trigger_sma": null,
      "last_checked": "2026-05-29T11:34:45.886474+00:00"
    },
    {
      "symbol": "NXPI",
      "added_date": "2026-05-29",
      "source": "earnings",
      "earnings_date": "2026-04-28",
      "earnings_gain_pct": 25.55,
      "earnings_close": 289.25,
      "high_30d": 244.04,
      "status": "watching",
      "sma_direction": "gaining",
      "current_sma": 331.844,
      "prev_sma": 331.584,
      "trigger_date": null,
      "trigger_price": null,
      "trigger_sma": null,
      "last_checked": "2026-05-29T11:34:46.014865+00:00"
    },
    {
      "symbol": "SBUX",
      "added_date": "2026-05-29",
      "source": "earnings",
      "earnings_date": "2026-04-28",
      "earnings_gain_pct": 8.45,
      "earnings_close": 104.8852,
      "high_30d": 99.4173,
      "status": "watching",
      "sma_direction": "declining",
      "current_sma": 101.585,
      "prev_sma": 101.728,
      "trigger_date": null,
      "trigger_price": null,
      "trigger_sma": null,
      "last_checked": "2026-05-29T11:34:46.139526+00:00"
    },
    {
      "symbol": "V",
      "added_date": "2026-05-29",
      "source": "earnings",
      "earnings_date": "2026-04-28",
      "earnings_gain_pct": 8.26,
      "earnings_close": 334.1672,
      "high_30d": 316.3641,
      "status": "watching",
      "sma_direction": "declining",
      "current_sma": 326.051,
      "prev_sma": 326.275,
      "trigger_date": null,
      "trigger_price": null,
      "trigger_sma": null,
      "last_checked": "2026-05-29T11:34:46.262723+00:00"
    },
    {
      "symbol": "ADP",
      "added_date": "2026-05-29",
      "source": "earnings",
      "earnings_date": "2026-04-29",
      "earnings_gain_pct": 7.98,
      "earnings_close": 215.06,
      "high_30d": 210.66,
      "status": "watching",
      "sma_direction": "declining",
      "current_sma": 218.639,
      "prev_sma": 218.899,
      "trigger_date": null,
      "trigger_price": null,
      "trigger_sma": null,
      "last_checked": "2026-05-29T11:34:46.385863+00:00"
    },
    {
      "symbol": "GOOG",
      "added_date": "2026-05-29",
      "source": "earnings",
      "earnings_date": "2026-04-29",
      "earnings_gain_pct": 9.97,
      "earnings_close": 381.94,
      "high_30d": 348.52,
      "status": "watching",
      "sma_direction": "gaining",
      "current_sma": 385.8076,
      "prev_sma": 385.1556,
      "trigger_date": null,
      "trigger_price": null,
      "trigger_sma": null,
      "last_checked": "2026-05-29T11:34:46.563909+00:00"
    },
    {
      "symbol": "GOOGL",
      "added_date": "2026-05-29",
      "source": "earnings",
      "earnings_date": "2026-04-29",
      "earnings_gain_pct": 9.96,
      "earnings_close": 384.8,
      "high_30d": 350.34,
      "status": "watching",
      "sma_direction": "gaining",
      "current_sma": 389.858,
      "prev_sma": 389.208,
      "trigger_date": null,
      "trigger_price": null,
      "trigger_sma": null,
      "last_checked": "2026-05-29T11:34:46.684412+00:00"
    },
    {
      "symbol": "HUM",
      "added_date": "2026-05-29",
      "source": "earnings",
      "earnings_date": "2026-04-29",
      "earnings_gain_pct": 5.83,
      "earnings_close": 243.12,
      "high_30d": 229.72,
      "status": "watching",
      "sma_direction": "gaining",
      "current_sma": 306.231,
      "prev_sma": 305.171,
      "trigger_date": null,
      "trigger_price": null,
      "trigger_sma": null,
      "last_checked": "2026-05-29T11:34:46.818505+00:00"
    },
    {
      "symbol": "ORLY",
      "added_date": "2026-05-29",
      "source": "earnings",
      "earnings_date": "2026-04-29",
      "earnings_gain_pct": 8.41,
      "earnings_close": 99.4,
      "high_30d": 94.4,
      "status": "watching",
      "sma_direction": "gaining",
      "current_sma": 89.081,
      "prev_sma": 88.938,
      "trigger_date": null,
      "trigger_price": null,
      "trigger_sma": null,
      "last_checked": "2026-05-29T11:34:46.961673+00:00"
    },
    {
      "symbol": "QCOM",
      "added_date": "2026-05-29",
      "source": "earnings",
      "earnings_date": "2026-04-29",
      "earnings_gain_pct": 15.12,
      "earnings_close": 179.58,
      "high_30d": 156,
      "status": "watching",
      "sma_direction": "declining",
      "current_sma": 240.092,
      "prev_sma": 241.4,
      "trigger_date": null,
      "trigger_price": null,
      "trigger_sma": null,
      "last_checked": "2026-05-29T11:34:47.082321+00:00"
    },
    {
      "symbol": "AIG",
      "added_date": "2026-05-29",
      "source": "earnings",
      "earnings_date": "2026-04-30",
      "earnings_gain_pct": 5.31,
      "earnings_close": 78.77,
      "high_30d": 78.68,
      "status": "watching",
      "sma_direction": "declining",
      "current_sma": 75.587,
      "prev_sma": 76.237,
      "trigger_date": null,
      "trigger_price": null,
      "trigger_sma": null,
      "last_checked": "2026-05-29T11:34:47.290037+00:00"
    },
    {
      "symbol": "CARR",
      "added_date": "2026-05-29",
      "source": "earnings",
      "earnings_date": "2026-04-30",
      "earnings_gain_pct": 8.79,
      "earnings_close": 66.9316,
      "high_30d": 64.4305,
      "status": "watching",
      "sma_direction": "declining",
      "current_sma": 64.5454,
      "prev_sma": 64.7674,
      "trigger_date": null,
      "trigger_price": null,
      "trigger_sma": null,
      "last_checked": "2026-05-29T11:34:47.424534+00:00"
    },
    {
      "symbol": "CAT",
      "added_date": "2026-05-29",
      "source": "earnings",
      "earnings_date": "2026-04-30",
      "earnings_gain_pct": 9.88,
      "earnings_close": 890.11,
      "high_30d": 835.24,
      "status": "watching",
      "sma_direction": "declining",
      "current_sma": 903.004,
      "prev_sma": 906.423,
      "trigger_date": null,
      "trigger_price": null,
      "trigger_sma": null,
      "last_checked": "2026-05-29T11:34:47.558614+00:00"
    },
    {
      "symbol": "MO",
      "added_date": "2026-05-29",
      "source": "earnings",
      "earnings_date": "2026-04-30",
      "earnings_gain_pct": 6.52,
      "earnings_close": 72.65,
      "high_30d": 68.2,
      "status": "watching",
      "sma_direction": "declining",
      "current_sma": 72.216,
      "prev_sma": 72.274,
      "trigger_date": null,
      "trigger_price": null,
      "trigger_sma": null,
      "last_checked": "2026-05-29T11:34:47.688795+00:00"
    },
    {
      "symbol": "TXT",
      "added_date": "2026-05-29",
      "source": "earnings",
      "earnings_date": "2026-04-30",
      "earnings_gain_pct": 6.88,
      "earnings_close": 95.96,
      "high_30d": 93.11,
      "status": "watching",
      "sma_direction": "declining",
      "current_sma": 92.511,
      "prev_sma": 92.646,
      "trigger_date": null,
      "trigger_price": null,
      "trigger_sma": null,
      "last_checked": "2026-05-29T11:34:47.816211+00:00"
    },
    {
      "symbol": "XEL",
      "added_date": "2026-05-29",
      "source": "earnings",
      "earnings_date": "2026-04-30",
      "earnings_gain_pct": 5.24,
      "earnings_close": 82.95,
      "high_30d": 82.77,
      "status": "watching",
      "sma_direction": "declining",
      "current_sma": 80.314,
      "prev_sma": 80.718,
      "trigger_date": null,
      "trigger_price": null,
      "trigger_sma": null,
      "last_checked": "2026-05-29T11:34:47.934133+00:00"
    },
    {
      "symbol": "CBOE",
      "added_date": "2026-05-29",
      "source": "earnings",
      "earnings_date": "2026-05-01",
      "earnings_gain_pct": 8.95,
      "earnings_close": 326.96,
      "high_30d": 309.38,
      "status": "watching",
      "sma_direction": "declining",
      "current_sma": 348.204,
      "prev_sma": 350.252,
      "trigger_date": null,
      "trigger_price": null,
      "trigger_sma": null,
      "last_checked": "2026-05-29T11:34:48.055511+00:00"
    },
    {
      "symbol": "TSN",
      "added_date": "2026-05-29",
      "source": "earnings",
      "earnings_date": "2026-05-04",
      "earnings_gain_pct": 7.96,
      "earnings_close": 68.75,
      "high_30d": 65.64,
      "status": "watching",
      "sma_direction": "declining",
      "current_sma": 64.579,
      "prev_sma": 65.29,
      "trigger_date": null,
      "trigger_price": null,
      "trigger_sma": null,
      "last_checked": "2026-05-29T11:34:48.178205+00:00"
    },
    {
      "symbol": "AMD",
      "added_date": "2026-05-29",
      "source": "earnings",
      "earnings_date": "2026-05-05",
      "earnings_gain_pct": 18.61,
      "earnings_close": 421.39,
      "high_30d": 360.54,
      "status": "watching",
      "sma_direction": "gaining",
      "current_sma": 506.2822,
      "prev_sma": 501.6732,
      "trigger_date": null,
      "trigger_price": null,
      "trigger_sma": null,
      "last_checked": "2026-05-29T11:34:48.315385+00:00"
    },
    {
      "symbol": "DD",
      "added_date": "2026-05-29",
      "source": "earnings",
      "earnings_date": "2026-05-05",
      "earnings_gain_pct": 8.43,
      "earnings_close": 49.0454,
      "high_30d": 47.6609,
      "status": "watching",
      "sma_direction": "declining",
      "current_sma": 48.059,
      "prev_sma": 48.365,
      "trigger_date": null,
      "trigger_price": null,
      "trigger_sma": null,
      "last_checked": "2026-05-29T11:34:48.437938+00:00"
    },
    {
      "symbol": "DOC",
      "added_date": "2026-05-29",
      "source": "earnings",
      "earnings_date": "2026-05-05",
      "earnings_gain_pct": 18.11,
      "earnings_close": 19.3973,
      "high_30d": 17.2785,
      "status": "watching",
      "sma_direction": "declining",
      "current_sma": 19.826,
      "prev_sma": 19.89,
      "trigger_date": null,
      "trigger_price": null,
      "trigger_sma": null,
      "last_checked": "2026-05-29T11:34:48.567722+00:00"
    },
    {
      "symbol": "EMR",
      "added_date": "2026-05-29",
      "source": "earnings",
      "earnings_date": "2026-05-05",
      "earnings_gain_pct": 6.94,
      "earnings_close": 147.3943,
      "high_30d": 146.1792,
      "status": "watching",
      "sma_direction": "gaining",
      "current_sma": 140.993,
      "prev_sma": 140.465,
      "trigger_date": null,
      "trigger_price": null,
      "trigger_sma": null,
      "last_checked": "2026-05-29T11:34:48.708123+00:00"
    },
    {
      "symbol": "ROK",
      "added_date": "2026-05-29",
      "source": "earnings",
      "earnings_date": "2026-05-05",
      "earnings_gain_pct": 8.9,
      "earnings_close": 434.5894,
      "high_30d": 414.4515,
      "status": "watching",
      "sma_direction": "gaining",
      "current_sma": 456.243,
      "prev_sma": 456.161,
      "trigger_date": null,
      "trigger_price": null,
      "trigger_sma": null,
      "last_checked": "2026-05-29T11:34:48.884479+00:00"
    },
    {
      "symbol": "WAT",
      "added_date": "2026-05-29",
      "source": "earnings",
      "earnings_date": "2026-05-05",
      "earnings_gain_pct": 13.54,
      "earnings_close": 342.75,
      "high_30d": 335.61,
      "status": "watching",
      "sma_direction": "gaining",
      "current_sma": 350.12,
      "prev_sma": 345,
      "trigger_date": null,
      "trigger_price": null,
      "trigger_sma": null,
      "last_checked": "2026-05-29T11:34:49.006948+00:00"
    },
    {
      "symbol": "APP",
      "added_date": "2026-05-29",
      "source": "earnings",
      "earnings_date": "2026-05-06",
      "earnings_gain_pct": 6.41,
      "earnings_close": 498.87,
      "high_30d": 490.96,
      "status": "watching",
      "sma_direction": "gaining",
      "current_sma": 571.85,
      "prev_sma": 554.056,
      "trigger_date": null,
      "trigger_price": null,
      "trigger_sma": null,
      "last_checked": "2026-05-29T11:34:49.135136+00:00"
    },
    {
      "symbol": "CVS",
      "added_date": "2026-05-29",
      "source": "earnings",
      "earnings_date": "2026-05-06",
      "earnings_gain_pct": 7.65,
      "earnings_close": 86.86,
      "high_30d": 83.9,
      "status": "watching",
      "sma_direction": "gaining",
      "current_sma": 92.105,
      "prev_sma": 91.761,
      "trigger_date": null,
      "trigger_price": null,
      "trigger_sma": null,
      "last_checked": "2026-05-29T11:34:49.285746+00:00"
    },
    {
      "symbol": "DIS",
      "added_date": "2026-05-29",
      "source": "earnings",
      "earnings_date": "2026-05-06",
      "earnings_gain_pct": 7.54,
      "earnings_close": 108.06,
      "high_30d": 106.3,
      "status": "watching",
      "sma_direction": "gaining",
      "current_sma": 103.759,
      "prev_sma": 103.609,
      "trigger_date": null,
      "trigger_price": null,
      "trigger_sma": null,
      "last_checked": "2026-05-29T11:34:49.417857+00:00"
    },
    {
      "symbol": "FTNT",
      "added_date": "2026-05-29",
      "source": "earnings",
      "earnings_date": "2026-05-06",
      "earnings_gain_pct": 20.03,
      "earnings_close": 107.97,
      "high_30d": 89.95,
      "status": "watching",
      "sma_direction": "declining",
      "current_sma": 129.888,
      "prev_sma": 130.913,
      "trigger_date": null,
      "trigger_price": null,
      "trigger_sma": null,
      "last_checked": "2026-05-29T11:34:49.540760+00:00"
    },
    {
      "symbol": "PTC",
      "added_date": "2026-05-29",
      "source": "earnings",
      "earnings_date": "2026-05-06",
      "earnings_gain_pct": 7.95,
      "earnings_close": 147.65,
      "high_30d": 144.36,
      "status": "watching",
      "sma_direction": "declining",
      "current_sma": 141.695,
      "prev_sma": 143.051,
      "trigger_date": null,
      "trigger_price": null,
      "trigger_sma": null,
      "last_checked": "2026-05-29T11:34:49.667707+00:00"
    },
    {
      "symbol": "UBER",
      "added_date": "2026-05-29",
      "source": "earnings",
      "earnings_date": "2026-05-06",
      "earnings_gain_pct": 8.53,
      "earnings_close": 79.17,
      "high_30d": 77.49,
      "status": "watching",
      "sma_direction": "gaining",
      "current_sma": 70.456,
      "prev_sma": 70.402,
      "trigger_date": null,
      "trigger_price": null,
      "trigger_sma": null,
      "last_checked": "2026-05-29T11:34:49.792238+00:00"
    },
    {
      "symbol": "AKAM",
      "added_date": "2026-05-29",
      "source": "earnings",
      "earnings_date": "2026-05-07",
      "earnings_gain_pct": 26.58,
      "earnings_close": 147.71,
      "high_30d": 121.99,
      "status": "watching",
      "sma_direction": "declining",
      "current_sma": 144.784,
      "prev_sma": 145.641,
      "trigger_date": null,
      "trigger_price": null,
      "trigger_sma": null,
      "last_checked": "2026-05-29T11:34:49.926866+00:00"
    },
    {
      "symbol": "DDOG",
      "added_date": "2026-05-29",
      "source": "earnings",
      "earnings_date": "2026-05-07",
      "earnings_gain_pct": 31.33,
      "earnings_close": 188.73,
      "high_30d": 146.69,
      "status": "watching",
      "sma_direction": "declining",
      "current_sma": 224.622,
      "prev_sma": 224.6471,
      "trigger_date": null,
      "trigger_price": null,
      "trigger_sma": null,
      "last_checked": "2026-05-29T11:34:50.095832+00:00"
    },
    {
      "symbol": "GEN",
      "added_date": "2026-05-29",
      "source": "earnings",
      "earnings_date": "2026-05-07",
      "earnings_gain_pct": 12.33,
      "earnings_close": 22.5591,
      "high_30d": 20.3112,
      "status": "watching",
      "sma_direction": "declining",
      "current_sma": 24.672,
      "prev_sma": 24.739,
      "trigger_date": null,
      "trigger_price": null,
      "trigger_sma": null,
      "last_checked": "2026-05-29T11:34:50.253255+00:00"
    },
    {
      "symbol": "MNST",
      "added_date": "2026-05-29",
      "source": "earnings",
      "earnings_date": "2026-05-07",
      "earnings_gain_pct": 13.58,
      "earnings_close": 86.29,
      "high_30d": 78.23,
      "status": "watching",
      "sma_direction": "gaining",
      "current_sma": 88.548,
      "prev_sma": 88.448,
      "trigger_date": null,
      "trigger_price": null,
      "trigger_sma": null,
      "last_checked": "2026-05-29T11:34:50.377240+00:00"
    },
    {
      "symbol": "VTRS",
      "added_date": "2026-05-29",
      "source": "earnings",
      "earnings_date": "2026-05-07",
      "earnings_gain_pct": 9.03,
      "earnings_close": 17.2632,
      "high_30d": 15.8337,
      "status": "watching",
      "sma_direction": "declining",
      "current_sma": 16.216,
      "prev_sma": 16.276,
      "trigger_date": null,
      "trigger_price": null,
      "trigger_sma": null,
      "last_checked": "2026-05-29T11:34:50.540303+00:00"
    },
    {
      "symbol": "XYZ",
      "added_date": "2026-05-29",
      "source": "earnings",
      "earnings_date": "2026-05-07",
      "earnings_gain_pct": 6.72,
      "earnings_close": 74.85,
      "high_30d": 73.89,
      "status": "watching",
      "sma_direction": "gaining",
      "current_sma": 71.843,
      "prev_sma": 70.7741,
      "trigger_date": null,
      "trigger_price": null,
      "trigger_sma": null,
      "last_checked": "2026-05-29T11:34:50.698725+00:00"
    },
    {
      "symbol": "FOX",
      "added_date": "2026-05-29",
      "source": "earnings",
      "earnings_date": "2026-05-11",
      "earnings_gain_pct": 8.09,
      "earnings_close": 61.18,
      "high_30d": 58.57,
      "status": "watching",
      "sma_direction": "gaining",
      "current_sma": 58.717,
      "prev_sma": 58.4415,
      "trigger_date": null,
      "trigger_price": null,
      "trigger_sma": null,
      "last_checked": "2026-05-29T11:34:50.829522+00:00"
    },
    {
      "symbol": "FOXA",
      "added_date": "2026-05-29",
      "source": "earnings",
      "earnings_date": "2026-05-11",
      "earnings_gain_pct": 7.59,
      "earnings_close": 67.72,
      "high_30d": 65.56,
      "status": "watching",
      "sma_direction": "gaining",
      "current_sma": 65.5244,
      "prev_sma": 65.3124,
      "trigger_date": null,
      "trigger_price": null,
      "trigger_sma": null,
      "last_checked": "2026-05-29T11:34:50.948300+00:00"
    },
    {
      "symbol": "Q",
      "added_date": "2026-05-29",
      "source": "earnings",
      "earnings_date": "2026-05-12",
      "earnings_gain_pct": 9.87,
      "earnings_close": 168.36,
      "high_30d": 153.24,
      "status": "watching",
      "sma_direction": "declining",
      "current_sma": 160.434,
      "prev_sma": 161.052,
      "trigger_date": null,
      "trigger_price": null,
      "trigger_sma": null,
      "last_checked": "2026-05-29T11:34:51.077594+00:00"
    },
    {
      "symbol": "CSCO",
      "added_date": "2026-05-29",
      "source": "earnings",
      "earnings_date": "2026-05-13",
      "earnings_gain_pct": 13.41,
      "earnings_close": 115.53,
      "high_30d": 101.87,
      "status": "watching",
      "sma_direction": "gaining",
      "current_sma": 119.036,
      "prev_sma": 118.856,
      "trigger_date": null,
      "trigger_price": null,
      "trigger_sma": null,
      "last_checked": "2026-05-29T11:34:51.243229+00:00"
    },
    {
      "symbol": "A",
      "added_date": "2026-05-29",
      "source": "earnings",
      "earnings_date": "2026-05-27",
      "earnings_gain_pct": 16.87,
      "earnings_close": 135.38,
      "high_30d": 122.09,
      "status": "watching",
      "sma_direction": "gaining",
      "current_sma": 123.488,
      "prev_sma": 119.392,
      "trigger_date": null,
      "trigger_price": null,
      "trigger_sma": null,
      "last_checked": "2026-05-29T11:34:51.412532+00:00"
    },
    {
      "symbol": "BBY",
      "added_date": "2026-05-29",
      "source": "earnings",
      "earnings_date": "2026-05-28",
      "earnings_gain_pct": 15.8,
      "earnings_close": 74.74,
      "high_30d": 66.94,
      "status": "watching",
      "sma_direction": "gaining",
      "current_sma": 68.474,
      "prev_sma": 66.058,
      "trigger_date": null,
      "trigger_price": null,
      "trigger_sma": null,
      "last_checked": "2026-05-29T11:34:51.537724+00:00"
    },
    {
      "symbol": "DLTR",
      "added_date": "2026-05-29",
      "source": "earnings",
      "earnings_date": "2026-05-28",
      "earnings_gain_pct": 17.87,
      "earnings_close": 113,
      "high_30d": 107.25,
      "status": "watching",
      "sma_direction": "gaining",
      "current_sma": 101.92,
      "prev_sma": 97.844,
      "trigger_date": null,
      "trigger_price": null,
      "trigger_sma": null,
      "last_checked": "2026-05-29T11:34:51.674588+00:00"
    },
    {
      "symbol": "HRL",
      "added_date": "2026-05-29",
      "source": "earnings",
      "earnings_date": "2026-05-28",
      "earnings_gain_pct": 12.55,
      "earnings_close": 23.59,
      "high_30d": 21.76,
      "status": "watching",
      "sma_direction": "gaining",
      "current_sma": 21.9852,
      "prev_sma": 21.4742,
      "trigger_date": null,
      "trigger_price": null,
      "trigger_sma": null,
      "last_checked": "2026-05-29T11:34:51.797314+00:00"
    }
  ]
}